demo_pip_math/__init__.py
demo_pip_math/math.py
tests/__init__.py
tests/test_math.py
demo_pip_math-0.2.0.dist-info/LICENSE
demo_pip_math-0.2.0.dist-info/METADATA
demo_pip_math-0.2.0.dist-info/WHEEL
demo_pip_math-0.2.0.dist-info/top_level.txt
demo_pip_math-0.2.0.dist-info/RECORD
