Metadata-Version: 2.1
Name: demo-pip-math
Version: 0.2.0
Summary: Demo your first Pip package.
Home-page: https://github.com/okeeffed/your-first-pip-package-in-python
Author: Dennis O'Keeffe
Author-email: hello@dennisokeeffe.com
License: UNKNOWN
Project-URL: Homepage, https://github.com/okeeffed/your-first-pip-package-in-python
Keywords: pip-demo math
Platform: UNKNOWN
Classifier: Programming Language :: Python :: 3
Classifier: License :: OSI Approved :: MIT License
Classifier: Operating System :: OS Independent
Requires-Python: >=3.6
License-File: LICENSE
